{
  "label": "SGB",
  "icon": "/mnt/SDCARD/Themes/SPRUCE/icons/sgb.png",
  "iconsel": "/mnt/SDCARD/Themes/SPRUCE/icons/sel/sgb.png",
  "launch": "launch.sh",
  "rompath": "../../Roms/SGB",
  "imgpath": "../../Roms/SGB/Imgs",
  "gamelist": "../../Roms/SGB/miyoogamelist.xml",
  "useswap": 1,
  "shortname": 0,
  "hidebios": 0,
  "extlist": "bin|gb|gbc|gba|zip|7z",
  "launchlist": [
    {
      "name": "Select Random Game",
      "launch": "/mnt/SDCARD/App/aleatorio/aleatorio.sh"
    },
    {
      "name": "CPU Mode: (✓SMART)-Performance-Overclock",
      "launch": "/mnt/SDCARD/Emu/.emu_setup/speed/Performance.sh"
    }
  ]
}
